mailnow/__init__.py
mailnow/client.py
mailnow/constants.py
mailnow/exceptions.py
mailnow/http_client.py
mailnow/validation.py
py_mailnow-0.1.0.dist-info/METADATA
py_mailnow-0.1.0.dist-info/WHEEL
py_mailnow-0.1.0.dist-info/RECORD
