Metadata-Version: 2.4
Name: py-mailnow
Version: 0.1.0
Summary: Python SDK for the Mailnow email API - send emails programmatically with a simple, type-safe interface
Project-URL: Homepage, https://mailnow.xyz
Project-URL: Documentation, https://github.com/mailnow/py-mailnow#readme
Project-URL: Repository, https://github.com/mailnow/py-mailnow
Project-URL: Issues, https://github.com/mailnow/py-mailnow/issues
Author-email: Mailnow <support@mailnow.xyz>
License: MIT
Keywords: api,email,email-api,mailnow,sdk
Classifier: Development Status :: 3 - Alpha
Classifier: Intended Audience :: Developers
Classifier: License :: OSI Approved :: MIT License
Classifier: Programming Language :: Python :: 3
Classifier: Programming Language :: Python :: 3.12
Classifier: Programming Language :: Python :: 3.13
Classifier: Topic :: Communications :: Email
Classifier: Topic :: Software Development :: Libraries :: Python Modules
Classifier: Typing :: Typed
Requires-Python: >=3.8
Requires-Dist: httpx>=0.27.0
Provides-Extra: dev
Requires-Dist: black>=24.0.0; extra == 'dev'
Requires-Dist: mypy>=1.8.0; extra == 'dev'
Requires-Dist: pytest-cov>=4.1.0; extra == 'dev'
Requires-Dist: pytest>=8.0.0; extra == 'dev'
Requires-Dist: respx>=0.21.0; extra == 'dev'
Requires-Dist: ruff>=0.2.0; extra == 'dev'
